{"directed": true, "multigraph": false, "graph": {}, "nodes": [{"id": "person.n.01"}, {"id": "adult.n.01"}, {"id": "object.n.01"}, {"id": "entity.n.01"}, {"id": "device.n.01"}, {"id": "air_conditioner.n.01"}, {"id": "clock.n.01"}, {"id": "alarm_clock.n.01"}, {"id": "animal.n.01"}, {"id": "tree.n.01"}, {"id": "apple.n.02"}, {"id": "avocado.n.02"}, {"id": "girl.n.01"}, {"id": "baby.n.05"}, {"id": "woman.n.01"}, {"id": "furniture.n.01"}, {"id": "baby_bed.n.01"}, {"id": "container.n.01"}, {"id": "baby_buggy.n.01"}, {"id": "shoe.n.01"}, {"id": "baby_shoe.n.01"}, {"id": "footwear.n.02"}, {"id": "bag.n.01"}, {"id": "backpack.n.01"}, {"id": "bread.n.01"}, {"id": "baguet.n.01"}, {"id": "food.n.02"}, {"id": "balcony.n.01"}, {"id": "ball.n.01"}, {"id": "conveyance.n.03"}, {"id": "balloon.n.01"}, {"id": "banana.n.02"}, {"id": "flag.n.01"}, {"id": "banner.n.01"}, {"id": "decoration.n.01"}, {"id": "counter.n.01"}, {"id": "bar.n.02"}, {"id": "table.n.02"}, {"id": "rack.n.01"}, {"id": "barbecue.n.03"}, {"id": "barrel.n.02"}, {"id": "game.n.01"}, {"id": "baseball.n.01"}, {"id": "bat.n.05"}, {"id": "baseball_bat.n.01"}, {"id": "stick.n.01"}, {"id": "sports_equipment.n.01"}, {"id": "baseball_glove.n.01"}, {"id": "basket.n.01"}, {"id": "basketball.n.02"}, {"id": "goal.n.03"}, {"id": "basket.n.03"}, {"id": "room.n.01"}, {"id": "toilet.n.01"}, {"id": "bathtub.n.01"}, {"id": "plaything.n.01"}, {"id": "beach_ball.n.01"}, {"id": "bead.n.01"}, {"id": "vegetable.n.01"}, {"id": "bean.n.01"}, {"id": "bear.n.01"}, {"id": "bed.n.01"}, {"id": "sheet.n.03"}, {"id": "bedroom.n.01"}, {"id": "bedspread.n.01"}, {"id": "bee.n.01"}, {"id": "belt.n.01"}, {"id": "seat.n.03"}, {"id": "bench.n.01"}, {"id": "bicycle.n.01"}, {"id": "motorcycle.n.01"}, {"id": "bin.n.01"}, {"id": "dame.n.01"}, {"id": "bird_feeder.n.01"}, {"id": "cage.n.01"}, {"id": "birdcage.n.01"}, {"id": "enclosure.n.01"}, {"id": "cake.n.03"}, {"id": "cookie.n.01"}, {"id": "black_box.n.01"}, {"id": "blackberry.n.02"}, {"id": "sheet.n.06"}, {"id": "blackboard.n.01"}, {"id": "blanket.n.01"}, {"id": "mixer.n.04"}, {"id": "blender.n.01"}, {"id": "kitchen_utensil.n.01"}, {"id": "utensil.n.01"}, {"id": "blind.n.03"}, {"id": "block.n.01"}, {"id": "shrub.n.01"}, {"id": "blueberry.n.01"}, {"id": "board.n.03"}, {"id": "board_game.n.01"}, {"id": "gravy_boat.n.01"}, {"id": "book.n.02"}, {"id": "bookcase.n.01"}, {"id": "shelf.n.01"}, {"id": "bookshelf.n.01"}, {"id": "bottle.n.01"}, {"id": "weapon.n.01"}, {"id": "bow.n.04"}, {"id": "bowl.n.03"}, {"id": "box.n.01"}, {"id": "man.n.01"}, {"id": "boy.n.02"}, {"id": "bracelet.n.02"}, {"id": "brick.n.02"}, {"id": "surface.n.01"}, {"id": "bridge.n.09"}, {"id": "broccoli.n.01"}, {"id": "broom.n.01"}, {"id": "brown_cup.n.01"}, {"id": "brush.n.02"}, {"id": "ball.n.03"}, {"id": "bubble.n.01"}, {"id": "bucket.n.01"}, {"id": "human_body.n.01"}, {"id": "building.n.01"}, {"id": "rabbit.n.01"}, {"id": "bunny.n.02"}, {"id": "bus.n.01"}, {"id": "butter.n.01"}, {"id": "butterfly.n.01"}, {"id": "cabinet.n.01"}, {"id": "cable.n.02"}, {"id": "cactus.n.01"}, {"id": "machine.n.01"}, {"id": "calculator.n.02"}, {"id": "calendar.n.01"}, {"id": "camel.n.01"}, {"id": "camera.n.01"}, {"id": "tool.n.01"}, {"id": "can_opener.n.01"}, {"id": "lamp.n.01"}, {"id": "candle.n.01"}, {"id": "candy.n.01"}, {"id": "candy_cane.n.01"}, {"id": "canister.n.02"}, {"id": "clothing.n.01"}, {"id": "cap.n.01"}, {"id": "car.n.01"}, {"id": "door.n.01"}, {"id": "car_door.n.01"}, {"id": "car_seat.n.01"}, {"id": "wheel.n.01"}, {"id": "car_wheel.n.01"}, {"id": "car_window.n.01"}, {"id": "cardboard.n.01"}, {"id": "card.n.04"}, {"id": "paper.n.01"}, {"id": "card_game.n.01"}, {"id": "rug.n.01"}, {"id": "carrot.n.02"}, {"id": "handcart.n.01"}, {"id": "cartoon.n.01"}, {"id": "case.n.05"}, {"id": "guy.n.01"}, {"id": "cat_food.n.01"}, {"id": "compact_disk.n.01"}, {"id": "ceiling.n.01"}, {"id": "grass.n.01"}, {"id": "cereal.n.01"}, {"id": "cereal_box.n.01"}, {"id": "necklace.n.01"}, {"id": "chain.n.09"}, {"id": "chair.n.01"}, {"id": "writing_implement.n.01"}, {"id": "chalk.n.04"}, {"id": "fixture.n.01"}, {"id": "chandelier.n.01"}, {"id": "horse.n.01"}, {"id": "charger.n.01"}, {"id": "tall_mallow.n.01"}, {"id": "chessboard.n.01"}, {"id": "chessman.n.01"}, {"id": "meat.n.01"}, {"id": "chicken.n.01"}, {"id": "child.n.01"}, {"id": "chimney.n.01"}, {"id": "tableware.n.01"}, {"id": "chopstick.n.01"}, {"id": "present.n.02"}, {"id": "christmas_present.n.01"}, {"id": "gift.n.01"}, {"id": "stocking.n.01"}, {"id": "christmas_stocking.n.01"}, {"id": "hosiery.n.01"}, {"id": "christmas_bush.n.01"}, {"id": "water_closet.n.01"}, {"id": "fabric.n.01"}, {"id": "cord.n.01"}, {"id": "clothesline.n.01"}, {"id": "clothespin.n.01"}, {"id": "cloud.n.01"}, {"id": "coat.n.01"}, {"id": "coatrack.n.01"}, {"id": "beverage.n.01"}, {"id": "coca_cola.n.01"}, {"id": "cup.n.01"}, {"id": "coffee_cup.n.01"}, {"id": "coffee_filter.n.01"}, {"id": "home_appliance.n.01"}, {"id": "coffee_maker.n.01"}, {"id": "mug.n.04"}, {"id": "coffee_mug.n.01"}, {"id": "coffee_table.n.01"}, {"id": "coin.n.01"}, {"id": "body_part.n.01"}, {"id": "comb.n.04"}, {"id": "computer.n.01"}, {"id": "monitor.n.04"}, {"id": "computer_monitor.n.01"}, {"id": "computer_screen.n.01"}, {"id": "cone.n.01"}, {"id": "control.n.09"}, {"id": "cookie_cutter.n.01"}, {"id": "corn.n.01"}, {"id": "sofa.n.01"}, {"id": "countertop.n.01"}, {"id": "cow.n.01"}, {"id": "crayon.n.01"}, {"id": "crib.n.01"}, {"id": "crocodile.n.01"}, {"id": "cube.n.04"}, {"id": "cuboid.n.01"}, {"id": "melon.n.02"}, {"id": "cucumber.n.01"}, {"id": "cupboard.n.01"}, {"id": "cupcake.n.01"}, {"id": "curtain.n.01"}, {"id": "shock_absorber.n.01"}, {"id": "chopping_board.n.01"}, {"id": "cylinder.n.02"}, {"id": "packet.n.03"}, {"id": "deck.n.02"}, {"id": "deer.n.01"}, {"id": "desk.n.01"}, {"id": "detergent.n.01"}, {"id": "diaper.n.01"}, {"id": "dining_table.n.01"}, {"id": "dinosaur.n.01"}, {"id": "disk.n.02"}, {"id": "dish.n.02"}, {"id": "dish_rack.n.01"}, {"id": "crockery.n.01"}, {"id": "dishwasher.n.01"}, {"id": "dog.n.01"}, {"id": "dog_food.n.01"}, {"id": "kennel.n.01"}, {"id": "house.n.01"}, {"id": "dollhouse.n.01"}, {"id": "fish.n.01"}, {"id": "dolphinfish.n.02"}, {"id": "doughnut.n.02"}, {"id": "switch.n.01"}, {"id": "doorbell.n.01"}, {"id": "doorframe.n.01"}, {"id": "dough.n.01"}, {"id": "dragon.n.02"}, {"id": "drawing_card.n.01"}, {"id": "drawer.n.01"}, {"id": "dress.n.01"}, {"id": "dressing_table.n.01"}, {"id": "monkey.n.01"}, {"id": "drill.n.02"}, {"id": "musical_instrument.n.01"}, {"id": "drum.n.01"}, {"id": "drumstick.n.02"}, {"id": "duck.n.01"}, {"id": "weight.n.02"}, {"id": "dumbbell.n.01"}, {"id": "dustpan.n.02"}, {"id": "earphone.n.01"}, {"id": "tripod.n.01"}, {"id": "easel.n.01"}, {"id": "egg.n.01"}, {"id": "egg_yolk.n.01"}, {"id": "eggplant.n.01"}, {"id": "electric_mixer.n.01"}, {"id": "elephant.n.01"}, {"id": "envelope.n.01"}, {"id": "exercise_bike.n.01"}, {"id": "face.n.04"}, {"id": "fan.n.01"}, {"id": "faucet.n.01"}, {"id": "feather.n.01"}, {"id": "fence.n.01"}, {"id": "file.n.03"}, {"id": "finger.n.01"}, {"id": "fireplace.n.01"}, {"id": "fire.n.04"}, {"id": "fire_extinguisher.n.01"}, {"id": "tube.n.01"}, {"id": "fireplug.n.01"}, {"id": "truck.n.01"}, {"id": "fire_engine.n.01"}, {"id": "aquarium.n.01"}, {"id": "fishbowl.n.02"}, {"id": "range_pole.n.01"}, {"id": "flamingo.n.01"}, {"id": "flashlight.n.01"}, {"id": "floor.n.02"}, {"id": "floor_lamp.n.01"}, {"id": "flower.n.01"}, {"id": "flowerbed.n.01"}, {"id": "booklet.n.01"}, {"id": "foundation.n.03"}, {"id": "football.n.02"}, {"id": "fork.n.01"}, {"id": "fox.n.01"}, {"id": "photograph.n.01"}, {"id": "frame.n.02"}, {"id": "refrigerator.n.01"}, {"id": "electric_refrigerator.n.01"}, {"id": "frisbee.n.01"}, {"id": "frog.n.01"}, {"id": "fruit.n.01"}, {"id": "yard.n.02"}, {"id": "garden.n.03"}, {"id": "garden_hose.n.01"}, {"id": "garlic.n.01"}, {"id": "gate.n.01"}, {"id": "ghost.n.01"}, {"id": "giraffe.n.01"}, {"id": "glass.n.07"}, {"id": "glass.n.02"}, {"id": "goat.n.01"}, {"id": "grapeshot.n.01"}, {"id": "grillroom.n.01"}, {"id": "land.n.04"}, {"id": "guitar.n.01"}, {"id": "hair.n.01"}, {"id": "hand_blower.n.01"}, {"id": "hairbrush.n.01"}, {"id": "mallet.n.02"}, {"id": "hammock.n.02"}, {"id": "hamster.n.01"}, {"id": "hired_hand.n.01"}, {"id": "bag.n.04"}, {"id": "handle.n.01"}, {"id": "harp.n.01"}, {"id": "hat.n.01"}, {"id": "heater.n.01"}, {"id": "helmet.n.01"}, {"id": "hockey_stick.n.01"}, {"id": "honeycomb.n.01"}, {"id": "ice_cream.n.01"}, {"id": "iron.n.02"}, {"id": "ironing_board.n.01"}, {"id": "jacket.n.01"}, {"id": "jar.n.01"}, {"id": "trouser.n.01"}, {"id": "jean.n.01"}, {"id": "puzzle.n.02"}, {"id": "jigsaw_puzzle.n.01"}, {"id": "reamer.n.01"}, {"id": "kangaroo.n.01"}, {"id": "pot.n.01"}, {"id": "kettle.n.01"}, {"id": "key.n.01"}, {"id": "keyboard.n.01"}, {"id": "kitchen.n.01"}, {"id": "kitchen_cabinet.n.01"}, {"id": "sink.n.01"}, {"id": "kitchen_sink.n.01"}, {"id": "kitchen_table.n.01"}, {"id": "kitchenware.n.01"}, {"id": "kite.n.03"}, {"id": "knife.n.02"}, {"id": "knob.n.01"}, {"id": "stairway.n.01"}, {"id": "ladder.n.01"}, {"id": "dame.n.02"}, {"id": "ladybug.n.01"}, {"id": "lampshade.n.01"}, {"id": "lantern.n.01"}, {"id": "laptop.n.01"}, {"id": "clothes_hamper.n.01"}, {"id": "lawn_mower.n.01"}, {"id": "leaf.n.01"}, {"id": "leg.n.03"}, {"id": "lego.n.01"}, {"id": "lemon.n.03"}, {"id": "letter.n.03"}, {"id": "lettuce.n.02"}, {"id": "light.n.02"}, {"id": "light_bulb.n.01"}, {"id": "lion.n.01"}, {"id": "llama.n.01"}, {"id": "log.n.05"}, {"id": "lollipop.n.02"}, {"id": "magazine.n.04"}, {"id": "mailbox.n.01"}, {"id": "mannequin.n.01"}, {"id": "marker.n.03"}, {"id": "mask.n.01"}, {"id": "mat.n.02"}, {"id": "pad.n.04"}, {"id": "mattress.n.01"}, {"id": "meter.n.02"}, {"id": "microphone.n.01"}, {"id": "microwave.n.02"}, {"id": "milk.n.01"}, {"id": "opal_glass.n.01"}, {"id": "mirror.n.01"}, {"id": "money.n.01"}, {"id": "moon.n.02"}, {"id": "swab.n.02"}, {"id": "mother.n.03"}, {"id": "mountain.n.01"}, {"id": "mouse.n.01"}, {"id": "mushroom.n.05"}, {"id": "music_box.n.01"}, {"id": "net.n.04"}, {"id": "newspaper.n.01"}, {"id": "notebook.n.01"}, {"id": "onion.n.02"}, {"id": "orange.n.03"}, {"id": "orange_peel.n.02"}, {"id": "stool.n.01"}, {"id": "footstool.n.01"}, {"id": "oven.n.01"}, {"id": "owl.n.01"}, {"id": "conciliator.n.01"}, {"id": "key.n.09"}, {"id": "paint_roller.n.01"}, {"id": "paintbrush.n.01"}, {"id": "painting.n.01"}, {"id": "palm.n.03"}, {"id": "pan.n.01"}, {"id": "pancake.n.01"}, {"id": "giant_panda.n.01"}, {"id": "sack.n.01"}, {"id": "dixie_cup.n.01"}, {"id": "paper_cutter.n.01"}, {"id": "paper_plate.n.01"}, {"id": "towel.n.01"}, {"id": "paper_towel.n.01"}, {"id": "parrot.n.01"}, {"id": "path.n.03"}, {"id": "patio.n.01"}, {"id": "sidewalk.n.01"}, {"id": "pea.n.01"}, {"id": "smasher.n.02"}, {"id": "pear.n.02"}, {"id": "playpen.n.01"}, {"id": "pencil.n.01"}, {"id": "pencil_box.n.01"}, {"id": "penguin.n.01"}, {"id": "people.n.01"}, {"id": "capsicum.n.01"}, {"id": "pepper_mill.n.01"}, {"id": "pepper_shaker.n.01"}, {"id": "pepperoni.n.01"}, {"id": "piano.n.01"}, {"id": "picture_frame.n.01"}, {"id": "hog.n.03"}, {"id": "piggy_bank.n.01"}, {"id": "pillar.n.03"}, {"id": "pillow.n.01"}, {"id": "pineapple.n.01"}, {"id": "wind_instrument.n.01"}, {"id": "pipe.n.04"}, {"id": "pizza.n.01"}, {"id": "airplane.n.01"}, {"id": "board.n.02"}, {"id": "plant.n.01"}, {"id": "plastic.n.01"}, {"id": "plastic_bag.n.01"}, {"id": "plastic_wrap.n.01"}, {"id": "plate.n.02"}, {"id": "playground.n.02"}, {"id": "slide.n.04"}, {"id": "pole.n.02"}, {"id": "pool.n.01"}, {"id": "pool_table.n.01"}, {"id": "popcorn.n.01"}, {"id": "porch.n.01"}, {"id": "post_horse.n.01"}, {"id": "pot_plant.n.01"}, {"id": "potato.n.02"}, {"id": "chip.n.04"}, {"id": "toilet.n.02"}, {"id": "power_line.n.01"}, {"id": "printer.n.02"}, {"id": "pug.n.01"}, {"id": "pumpkin.n.01"}, {"id": "puppet.n.03"}, {"id": "racket.n.04"}, {"id": "radiator.n.02"}, {"id": "railing.n.01"}, {"id": "rainbow.n.01"}, {"id": "ramp.n.01"}, {"id": "record_player.n.01"}, {"id": "recycling_bin.n.01"}, {"id": "caribou.n.01"}, {"id": "remote_control.n.01"}, {"id": "ribbon.n.01"}, {"id": "hoop.n.02"}, {"id": "ascent.n.01"}, {"id": "road.n.01"}, {"id": "automaton.n.02"}, {"id": "rock.n.01"}, {"id": "roller.n.03"}, {"id": "ceiling.n.03"}, {"id": "rope.n.01"}, {"id": "round_table.n.01"}, {"id": "rule.n.12"}, {"id": "salt.n.02"}, {"id": "saltshaker.n.01"}, {"id": "sand.n.01"}, {"id": "sandal.n.01"}, {"id": "sandwich.n.01"}, {"id": "sauce.n.01"}, {"id": "saucepan.n.01"}, {"id": "scale.n.07"}, {"id": "scissors.n.01"}, {"id": "scoter.n.01"}, {"id": "screwdriver.n.01"}, {"id": "gull.n.02"}, {"id": "seashell.n.01"}, {"id": "seat_belt.n.01"}, {"id": "tail.n.05"}, {"id": "shark.n.01"}, {"id": "shed.n.01"}, {"id": "sheep.n.01"}, {"id": "shirt.n.01"}, {"id": "shopping_cart.n.01"}, {"id": "short.n.01"}, {"id": "power_shovel.n.01"}, {"id": "shower.n.01"}, {"id": "shower_curtain.n.01"}, {"id": "signboard.n.01"}, {"id": "silverware.n.01"}, {"id": "skateboard.n.01"}, {"id": "skeleton.n.04"}, {"id": "sky.n.01"}, {"id": "slide.n.01"}, {"id": "slipper.n.01"}, {"id": "snake.n.01"}, {"id": "snow.n.02"}, {"id": "snow_bunting.n.01"}, {"id": "snowman.n.01"}, {"id": "soap.n.01"}, {"id": "soap_dish.n.01"}, {"id": "soap_dispenser.n.01"}, {"id": "soccer_ball.n.01"}, {"id": "sock.n.01"}, {"id": "convertible.n.03"}, {"id": "land.n.02"}, {"id": "soup.n.01"}, {"id": "soup_bowl.n.01"}, {"id": "spoon.n.01"}, {"id": "soupspoon.n.01"}, {"id": "spatula.n.01"}, {"id": "speaker.n.01"}, {"id": "spider.n.03"}, {"id": "sponge.n.01"}, {"id": "spray.n.03"}, {"id": "step.n.04"}, {"id": "star.n.01"}, {"id": "starfish.n.01"}, {"id": "steering_wheel.n.01"}, {"id": "dagger.n.01"}, {"id": "stone_wall.n.01"}, {"id": "stove.n.02"}, {"id": "strap.n.04"}, {"id": "straw.n.04"}, {"id": "strawberry.n.02"}, {"id": "street.n.01"}, {"id": "bowed_stringed_instrument.n.01"}, {"id": "bag.n.06"}, {"id": "sunglass.n.01"}, {"id": "sushi.n.01"}, {"id": "swan.n.01"}, {"id": "sweater.n.01"}, {"id": "swing.n.02"}, {"id": "switchboard.n.01"}, {"id": "table_lamp.n.01"}, {"id": "table_mat.n.01"}, {"id": "tablecloth.n.01"}, {"id": "tablet.n.03"}, {"id": "tambourine.n.01"}, {"id": "tap.n.04"}, {"id": "tape.n.04"}, {"id": "teapot.n.01"}, {"id": "teddy.n.01"}, {"id": "electronic_equipment.n.01"}, {"id": "telephone.n.01"}, {"id": "telephone_wire.n.01"}, {"id": "telephone_cord.n.01"}, {"id": "wire.n.02"}, {"id": "telephone_pole.n.01"}, {"id": "telephone_receiver.n.01"}, {"id": "television.n.02"}, {"id": "tennis_ball.n.01"}, {"id": "tennis_racket.n.01"}, {"id": "tent.n.01"}, {"id": "tiger.n.01"}, {"id": "tile.n.01"}, {"id": "tire.n.01"}, {"id": "tissue.n.01"}, {"id": "tissue.n.02"}, {"id": "toaster.n.01"}, {"id": "toaster_oven.n.01"}, {"id": "toddler.n.01"}, {"id": "toilet_tissue.n.01"}, {"id": "toilet_seat.n.01"}, {"id": "tomato.n.01"}, {"id": "tomato_sauce.n.01"}, {"id": "toolbox.n.01"}, {"id": "toothbrush.n.01"}, {"id": "toothpaste.n.01"}, {"id": "towel_rack.n.01"}, {"id": "tugboat.n.01"}, {"id": "toy_box.n.01"}, {"id": "toy_dog.n.01"}, {"id": "path.n.04"}, {"id": "train.n.01"}, {"id": "train_set.n.01"}, {"id": "trampoline.n.01"}, {"id": "rubbish.n.01"}, {"id": "ashcan.n.01"}, {"id": "tray.n.01"}, {"id": "treadmill.n.02"}, {"id": "trunk.n.01"}, {"id": "triangle.n.04"}, {"id": "tricycle.n.01"}, {"id": "streetcar.n.01"}, {"id": "tunnel.n.01"}, {"id": "turtleneck.n.01"}, {"id": "ballet_skirt.n.01"}, {"id": "television.n.01"}, {"id": "uke.n.01"}, {"id": "umbrella.n.01"}, {"id": "unicorn.n.01"}, {"id": "vacuum.n.04"}, {"id": "van.n.03"}, {"id": "vase.n.01"}, {"id": "violin.n.01"}, {"id": "walker.n.04"}, {"id": "wall.n.07"}, {"id": "wall_clock.n.01"}, {"id": "hanging.n.01"}, {"id": "wall_socket.n.01"}, {"id": "wallet.n.01"}, {"id": "wardrobe.n.01"}, {"id": "washer.n.01"}, {"id": "washer.n.03"}, {"id": "body_of_water.n.01"}, {"id": "water_bottle.n.01"}, {"id": "drinking_fountain.n.01"}, {"id": "water_clock.n.01"}, {"id": "water_pistol.n.01"}, {"id": "water_jug.n.01"}, {"id": "hookah.n.01"}, {"id": "water_pump.n.01"}, {"id": "water_table.n.01"}, {"id": "cistern.n.02"}, {"id": "water_faucet.n.01"}, {"id": "watering_can.n.01"}, {"id": "watermelon.n.01"}, {"id": "barrow.n.03"}, {"id": "wheelchair.n.01"}, {"id": "whisk.n.01"}, {"id": "wicker_basket.n.01"}, {"id": "window.n.01"}, {"id": "window_blind.n.01"}, {"id": "window_frame.n.01"}, {"id": "pane.n.01"}, {"id": "window_screen.n.01"}, {"id": "window_shade.n.01"}, {"id": "wine_bottle.n.01"}, {"id": "thread.n.01"}, {"id": "zebra.n.01"}, {"id": "watch.n.01"}, {"id": "basement.n.01"}, {"id": "sandbox.n.01"}, {"id": "toe.n.01"}, {"id": "chewing_gum.n.01"}, {"id": "jello.n.01"}, {"id": "sled.n.01"}, {"id": "dryer.n.01"}, {"id": "boot.n.02"}, {"id": "bib.n.01"}, {"id": "pajama.n.01"}, {"id": "adieu.n.01"}, {"id": "alligator.n.02"}, {"id": "mitten.n.01"}, {"id": "nail.n.01"}, {"id": "gym_shoe.n.01"}, {"id": "radio_receiver.n.01"}, {"id": "gelatin.n.02"}, {"id": "glue.n.01"}, {"id": "squirrel.n.01"}, {"id": "pudding.n.01"}, {"id": "ice_lolly.n.01"}, {"id": "cock.n.04"}, {"id": "head.n.01"}, {"id": "brim.n.01"}, {"id": "cracker.n.01"}, {"id": "yogurt.n.01"}, {"id": "pickle.n.01"}, {"id": "coffee.n.02"}, {"id": "pretzel.n.01"}, {"id": "penis.n.01"}, {"id": "sprinkler.n.01"}, {"id": "muffin.n.01"}, {"id": "tooth.n.01"}, {"id": "pony.n.01"}, {"id": "bug.n.03"}, {"id": "scarf.n.01"}, {"id": "wolf.n.04"}, {"id": "kitten.n.01"}, {"id": "turkey.n.01"}, {"id": "nose.n.02"}, {"id": "ankle.n.01"}, {"id": "tractor.n.02"}, {"id": "hamburger.n.01"}, {"id": "raisin.n.01"}, {"id": "vanilla.n.01"}, {"id": "stomach.n.01"}, {"id": "nut.n.01"}, {"id": "auricle.n.02"}, {"id": "hen.n.01"}, {"id": "button.n.01"}, {"id": "pop.n.02"}, {"id": "juice.n.01"}, {"id": "mouth.n.01"}, {"id": "garage.n.01"}, {"id": "ice.n.01"}, {"id": "penny.n.02"}, {"id": "cheek.n.01"}, {"id": "spit.n.01"}, {"id": "eye.n.01"}, {"id": "applesauce.n.01"}, {"id": "snowsuit.n.01"}, {"id": "butt.n.08"}, {"id": "pasta.n.01"}, {"id": "helicopter.n.01"}, {"id": "slide_fastener.n.01"}, {"id": "pastry.n.01"}, {"id": "cocoa.n.01"}, {"id": "medicine.n.01"}, {"id": "rain.n.01"}, {"id": "vitamin.n.01"}, {"id": "goose.n.01"}, {"id": "toast.n.01"}, {"id": "vagina.n.01"}, {"id": "ant.n.01"}, {"id": "elk.n.01"}, {"id": "lamb.n.01"}, {"id": "shoulder.n.02"}, {"id": "tuna.n.01"}, {"id": "puppy.n.01"}, {"id": "knee.n.01"}, {"id": "sport.n.03"}], "links": [{"source": "person.n.01", "target": "adult.n.01"}, {"source": "person.n.01", "target": "brick.n.02"}, {"source": "person.n.01", "target": "child.n.01"}, {"source": "person.n.01", "target": "dragon.n.02"}, {"source": "person.n.01", "target": "drawing_card.n.01"}, {"source": "person.n.01", "target": "hired_hand.n.01"}, {"source": "person.n.01", "target": "letter.n.03"}, {"source": "person.n.01", "target": "mannequin.n.01"}, {"source": "person.n.01", "target": "conciliator.n.01"}, {"source": "person.n.01", "target": "pillar.n.03"}, {"source": "person.n.01", "target": "pole.n.02"}, {"source": "person.n.01", "target": "tail.n.05"}, {"source": "person.n.01", "target": "speaker.n.01"}, {"source": "person.n.01", "target": "tiger.n.01"}, {"source": "person.n.01", "target": "toaster.n.01"}, {"source": "person.n.01", "target": "washer.n.01"}, {"source": "person.n.01", "target": "sport.n.03"}, {"source": "adult.n.01", "target": "woman.n.01"}, {"source": "adult.n.01", "target": "man.n.01"}, {"source": "object.n.01", "target": "person.n.01"}, {"source": "object.n.01", "target": "device.n.01"}, {"source": "object.n.01", "target": "animal.n.01"}, {"source": "object.n.01", "target": "tree.n.01"}, {"source": "object.n.01", "target": "furniture.n.01"}, {"source": "object.n.01", "target": "container.n.01"}, {"source": "object.n.01", "target": "footwear.n.02"}, {"source": "object.n.01", "target": "balcony.n.01"}, {"source": "object.n.01", "target": "ball.n.01"}, {"source": "object.n.01", "target": "conveyance.n.03"}, {"source": "object.n.01", "target": "decoration.n.01"}, {"source": "object.n.01", "target": "rack.n.01"}, {"source": "object.n.01", "target": "stick.n.01"}, {"source": "object.n.01", "target": "sports_equipment.n.01"}, {"source": "object.n.01", "target": "goal.n.03"}, {"source": "object.n.01", "target": "room.n.01"}, {"source": "object.n.01", "target": "plaything.n.01"}, {"source": "object.n.01", "target": "sheet.n.03"}, {"source": "object.n.01", "target": "bedspread.n.01"}, {"source": "object.n.01", "target": "enclosure.n.01"}, {"source": "object.n.01", "target": "black_box.n.01"}, {"source": "object.n.01", "target": "blackberry.n.02"}, {"source": "object.n.01", "target": "sheet.n.06"}, {"source": "object.n.01", "target": "blanket.n.01"}, {"source": "object.n.01", "target": "utensil.n.01"}, {"source": "object.n.01", "target": "blind.n.03"}, {"source": "object.n.01", "target": "block.n.01"}, {"source": "object.n.01", "target": "shrub.n.01"}, {"source": "object.n.01", "target": "book.n.02"}, {"source": "object.n.01", "target": "surface.n.01"}, {"source": "object.n.01", "target": "broccoli.n.01"}, {"source": "object.n.01", "target": "broom.n.01"}, {"source": "object.n.01", "target": "brown_cup.n.01"}, {"source": "object.n.01", "target": "brush.n.02"}, {"source": "object.n.01", "target": "human_body.n.01"}, {"source": "object.n.01", "target": "building.n.01"}, {"source": "object.n.01", "target": "cactus.n.01"}, {"source": "object.n.01", "target": "camera.n.01"}, {"source": "object.n.01", "target": "tool.n.01"}, {"source": "object.n.01", "target": "clothing.n.01"}, {"source": "object.n.01", "target": "door.n.01"}, {"source": "object.n.01", "target": "car_window.n.01"}, {"source": "object.n.01", "target": "rug.n.01"}, {"source": "object.n.01", "target": "carrot.n.02"}, {"source": "object.n.01", "target": "grass.n.01"}, {"source": "object.n.01", "target": "writing_implement.n.01"}, {"source": "object.n.01", "target": "fixture.n.01"}, {"source": "object.n.01", "target": "chessman.n.01"}, {"source": "object.n.01", "target": "chimney.n.01"}, {"source": "object.n.01", "target": "tableware.n.01"}, {"source": "object.n.01", "target": "fabric.n.01"}, {"source": "object.n.01", "target": "cord.n.01"}, {"source": "object.n.01", "target": "home_appliance.n.01"}, {"source": "object.n.01", "target": "cone.n.01"}, {"source": "object.n.01", "target": "melon.n.02"}, {"source": "object.n.01", "target": "cupboard.n.01"}, {"source": "object.n.01", "target": "kennel.n.01"}, {"source": "object.n.01", "target": "doorframe.n.01"}, {"source": "object.n.01", "target": "drawer.n.01"}, {"source": "object.n.01", "target": "egg.n.01"}, {"source": "object.n.01", "target": "feather.n.01"}, {"source": "object.n.01", "target": "fence.n.01"}, {"source": "object.n.01", "target": "tube.n.01"}, {"source": "object.n.01", "target": "floor.n.02"}, {"source": "object.n.01", "target": "flower.n.01"}, {"source": "object.n.01", "target": "flowerbed.n.01"}, {"source": "object.n.01", "target": "booklet.n.01"}, {"source": "object.n.01", "target": "foundation.n.03"}, {"source": "object.n.01", "target": "photograph.n.01"}, {"source": "object.n.01", "target": "fruit.n.01"}, {"source": "object.n.01", "target": "yard.n.02"}, {"source": "object.n.01", "target": "garlic.n.01"}, {"source": "object.n.01", "target": "gate.n.01"}, {"source": "object.n.01", "target": "land.n.04"}, {"source": "object.n.01", "target": "hair.n.01"}, {"source": "object.n.01", "target": "handle.n.01"}, {"source": "object.n.01", "target": "helmet.n.01"}, {"source": "object.n.01", "target": "honeycomb.n.01"}, {"source": "object.n.01", "target": "puzzle.n.02"}, {"source": "object.n.01", "target": "knob.n.01"}, {"source": "object.n.01", "target": "stairway.n.01"}, {"source": "object.n.01", "target": "lampshade.n.01"}, {"source": "object.n.01", "target": "leaf.n.01"}, {"source": "object.n.01", "target": "lettuce.n.02"}, {"source": "object.n.01", "target": "mat.n.02"}, {"source": "object.n.01", "target": "pad.n.04"}, {"source": "object.n.01", "target": "moon.n.02"}, {"source": "object.n.01", "target": "swab.n.02"}, {"source": "object.n.01", "target": "mountain.n.01"}, {"source": "object.n.01", "target": "newspaper.n.01"}, {"source": "object.n.01", "target": "onion.n.02"}, {"source": "object.n.01", "target": "key.n.09"}, {"source": "object.n.01", "target": "painting.n.01"}, {"source": "object.n.01", "target": "path.n.03"}, {"source": "object.n.01", "target": "patio.n.01"}, {"source": "object.n.01", "target": "sidewalk.n.01"}, {"source": "object.n.01", "target": "picture_frame.n.01"}, {"source": "object.n.01", "target": "pillow.n.01"}, {"source": "object.n.01", "target": "pineapple.n.01"}, {"source": "object.n.01", "target": "board.n.02"}, {"source": "object.n.01", "target": "plant.n.01"}, {"source": "object.n.01", "target": "plastic_wrap.n.01"}, {"source": "object.n.01", "target": "pool.n.01"}, {"source": "object.n.01", "target": "porch.n.01"}, {"source": "object.n.01", "target": "pot_plant.n.01"}, {"source": "object.n.01", "target": "potato.n.02"}, {"source": "object.n.01", "target": "pumpkin.n.01"}, {"source": "object.n.01", "target": "racket.n.04"}, {"source": "object.n.01", "target": "railing.n.01"}, {"source": "object.n.01", "target": "ribbon.n.01"}, {"source": "object.n.01", "target": "hoop.n.02"}, {"source": "object.n.01", "target": "ascent.n.01"}, {"source": "object.n.01", "target": "road.n.01"}, {"source": "object.n.01", "target": "rock.n.01"}, {"source": "object.n.01", "target": "rope.n.01"}, {"source": "object.n.01", "target": "seashell.n.01"}, {"source": "object.n.01", "target": "short.n.01"}, {"source": "object.n.01", "target": "signboard.n.01"}, {"source": "object.n.01", "target": "skeleton.n.04"}, {"source": "object.n.01", "target": "snow.n.02"}, {"source": "object.n.01", "target": "snowman.n.01"}, {"source": "object.n.01", "target": "land.n.02"}, {"source": "object.n.01", "target": "star.n.01"}, {"source": "object.n.01", "target": "strawberry.n.02"}, {"source": "object.n.01", "target": "switchboard.n.01"}, {"source": "object.n.01", "target": "tablecloth.n.01"}, {"source": "object.n.01", "target": "electronic_equipment.n.01"}, {"source": "object.n.01", "target": "television.n.02"}, {"source": "object.n.01", "target": "tent.n.01"}, {"source": "object.n.01", "target": "path.n.04"}, {"source": "object.n.01", "target": "trunk.n.01"}, {"source": "object.n.01", "target": "tunnel.n.01"}, {"source": "object.n.01", "target": "television.n.01"}, {"source": "object.n.01", "target": "umbrella.n.01"}, {"source": "object.n.01", "target": "wall_socket.n.01"}, {"source": "object.n.01", "target": "drinking_fountain.n.01"}, {"source": "object.n.01", "target": "water_table.n.01"}, {"source": "object.n.01", "target": "window.n.01"}, {"source": "object.n.01", "target": "window_frame.n.01"}, {"source": "object.n.01", "target": "window_screen.n.01"}, {"source": "object.n.01", "target": "dryer.n.01"}, {"source": "entity.n.01", "target": "object.n.01"}, {"source": "entity.n.01", "target": "food.n.02"}, {"source": "entity.n.01", "target": "game.n.01"}, {"source": "entity.n.01", "target": "belt.n.01"}, {"source": "entity.n.01", "target": "ball.n.03"}, {"source": "entity.n.01", "target": "butter.n.01"}, {"source": "entity.n.01", "target": "calendar.n.01"}, {"source": "entity.n.01", "target": "candy.n.01"}, {"source": "entity.n.01", "target": "paper.n.01"}, {"source": "entity.n.01", "target": "cartoon.n.01"}, {"source": "entity.n.01", "target": "cat_food.n.01"}, {"source": "entity.n.01", "target": "gift.n.01"}, {"source": "entity.n.01", "target": "cloud.n.01"}, {"source": "entity.n.01", "target": "beverage.n.01"}, {"source": "entity.n.01", "target": "coin.n.01"}, {"source": "entity.n.01", "target": "body_part.n.01"}, {"source": "entity.n.01", "target": "cuboid.n.01"}, {"source": "entity.n.01", "target": "cylinder.n.02"}, {"source": "entity.n.01", "target": "detergent.n.01"}, {"source": "entity.n.01", "target": "dish.n.02"}, {"source": "entity.n.01", "target": "dog_food.n.01"}, {"source": "entity.n.01", "target": "dough.n.01"}, {"source": "entity.n.01", "target": "egg_yolk.n.01"}, {"source": "entity.n.01", "target": "ghost.n.01"}, {"source": "entity.n.01", "target": "ice_cream.n.01"}, {"source": "entity.n.01", "target": "kitchen_cabinet.n.01"}, {"source": "entity.n.01", "target": "opal_glass.n.01"}, {"source": "entity.n.01", "target": "money.n.01"}, {"source": "entity.n.01", "target": "orange_peel.n.02"}, {"source": "entity.n.01", "target": "paint_roller.n.01"}, {"source": "entity.n.01", "target": "people.n.01"}, {"source": "entity.n.01", "target": "plastic.n.01"}, {"source": "entity.n.01", "target": "rainbow.n.01"}, {"source": "entity.n.01", "target": "ceiling.n.03"}, {"source": "entity.n.01", "target": "round_table.n.01"}, {"source": "entity.n.01", "target": "salt.n.02"}, {"source": "entity.n.01", "target": "sand.n.01"}, {"source": "entity.n.01", "target": "sauce.n.01"}, {"source": "entity.n.01", "target": "sky.n.01"}, {"source": "entity.n.01", "target": "soap.n.01"}, {"source": "entity.n.01", "target": "sponge.n.01"}, {"source": "entity.n.01", "target": "toothpaste.n.01"}, {"source": "entity.n.01", "target": "rubbish.n.01"}, {"source": "entity.n.01", "target": "unicorn.n.01"}, {"source": "entity.n.01", "target": "body_of_water.n.01"}, {"source": "entity.n.01", "target": "chewing_gum.n.01"}, {"source": "entity.n.01", "target": "jello.n.01"}, {"source": "entity.n.01", "target": "adieu.n.01"}, {"source": "entity.n.01", "target": "gelatin.n.02"}, {"source": "entity.n.01", "target": "glue.n.01"}, {"source": "entity.n.01", "target": "ice_lolly.n.01"}, {"source": "entity.n.01", "target": "yogurt.n.01"}, {"source": "entity.n.01", "target": "pickle.n.01"}, {"source": "entity.n.01", "target": "juice.n.01"}, {"source": "entity.n.01", "target": "ice.n.01"}, {"source": "entity.n.01", "target": "medicine.n.01"}, {"source": "entity.n.01", "target": "rain.n.01"}, {"source": "entity.n.01", "target": "vitamin.n.01"}, {"source": "device.n.01", "target": "air_conditioner.n.01"}, {"source": "device.n.01", "target": "clock.n.01"}, {"source": "device.n.01", "target": "bird_feeder.n.01"}, {"source": "device.n.01", "target": "shelf.n.01"}, {"source": "device.n.01", "target": "weapon.n.01"}, {"source": "device.n.01", "target": "cable.n.02"}, {"source": "device.n.01", "target": "machine.n.01"}, {"source": "device.n.01", "target": "lamp.n.01"}, {"source": "device.n.01", "target": "car_seat.n.01"}, {"source": "device.n.01", "target": "wheel.n.01"}, {"source": "device.n.01", "target": "compact_disk.n.01"}, {"source": "device.n.01", "target": "clothespin.n.01"}, {"source": "device.n.01", "target": "coffee_filter.n.01"}, {"source": "device.n.01", "target": "monitor.n.04"}, {"source": "device.n.01", "target": "computer_screen.n.01"}, {"source": "device.n.01", "target": "control.n.09"}, {"source": "device.n.01", "target": "shock_absorber.n.01"}, {"source": "device.n.01", "target": "disk.n.02"}, {"source": "device.n.01", "target": "musical_instrument.n.01"}, {"source": "device.n.01", "target": "earphone.n.01"}, {"source": "device.n.01", "target": "tripod.n.01"}, {"source": "device.n.01", "target": "exercise_bike.n.01"}, {"source": "device.n.01", "target": "fan.n.01"}, {"source": "device.n.01", "target": "fire_extinguisher.n.01"}, {"source": "device.n.01", "target": "range_pole.n.01"}, {"source": "device.n.01", "target": "hand_blower.n.01"}, {"source": "device.n.01", "target": "heater.n.01"}, {"source": "device.n.01", "target": "key.n.01"}, {"source": "device.n.01", "target": "keyboard.n.01"}, {"source": "device.n.01", "target": "leg.n.03"}, {"source": "device.n.01", "target": "light.n.02"}, {"source": "device.n.01", "target": "log.n.05"}, {"source": "device.n.01", "target": "magazine.n.04"}, {"source": "device.n.01", "target": "meter.n.02"}, {"source": "device.n.01", "target": "microphone.n.01"}, {"source": "device.n.01", "target": "mirror.n.01"}, {"source": "device.n.01", "target": "ramp.n.01"}, {"source": "device.n.01", "target": "remote_control.n.01"}, {"source": "device.n.01", "target": "automaton.n.02"}, {"source": "device.n.01", "target": "rule.n.12"}, {"source": "device.n.01", "target": "scale.n.07"}, {"source": "device.n.01", "target": "seat_belt.n.01"}, {"source": "device.n.01", "target": "step.n.04"}, {"source": "device.n.01", "target": "strap.n.04"}, {"source": "device.n.01", "target": "sunglass.n.01"}, {"source": "device.n.01", "target": "swing.n.02"}, {"source": "device.n.01", "target": "tape.n.04"}, {"source": "device.n.01", "target": "wire.n.02"}, {"source": "device.n.01", "target": "telephone_pole.n.01"}, {"source": "device.n.01", "target": "triangle.n.04"}, {"source": "device.n.01", "target": "water_pump.n.01"}, {"source": "device.n.01", "target": "watch.n.01"}, {"source": "device.n.01", "target": "sprinkler.n.01"}, {"source": "device.n.01", "target": "button.n.01"}, {"source": "device.n.01", "target": "slide_fastener.n.01"}, {"source": "clock.n.01", "target": "alarm_clock.n.01"}, {"source": "clock.n.01", "target": "wall_clock.n.01"}, {"source": "clock.n.01", "target": "water_clock.n.01"}, {"source": "animal.n.01", "target": "bear.n.01"}, {"source": "animal.n.01", "target": "bee.n.01"}, {"source": "animal.n.01", "target": "rabbit.n.01"}, {"source": "animal.n.01", "target": "butterfly.n.01"}, {"source": "animal.n.01", "target": "camel.n.01"}, {"source": "animal.n.01", "target": "horse.n.01"}, {"source": "animal.n.01", "target": "cow.n.01"}, {"source": "animal.n.01", "target": "crocodile.n.01"}, {"source": "animal.n.01", "target": "deer.n.01"}, {"source": "animal.n.01", "target": "dinosaur.n.01"}, {"source": "animal.n.01", "target": "dog.n.01"}, {"source": "animal.n.01", "target": "fish.n.01"}, {"source": "animal.n.01", "target": "monkey.n.01"}, {"source": "animal.n.01", "target": "duck.n.01"}, {"source": "animal.n.01", "target": "elephant.n.01"}, {"source": "animal.n.01", "target": "flamingo.n.01"}, {"source": "animal.n.01", "target": "fox.n.01"}, {"source": "animal.n.01", "target": "frog.n.01"}, {"source": "animal.n.01", "target": "giraffe.n.01"}, {"source": "animal.n.01", "target": "goat.n.01"}, {"source": "animal.n.01", "target": "hamster.n.01"}, {"source": "animal.n.01", "target": "kangaroo.n.01"}, {"source": "animal.n.01", "target": "ladybug.n.01"}, {"source": "animal.n.01", "target": "lion.n.01"}, {"source": "animal.n.01", "target": "llama.n.01"}, {"source": "animal.n.01", "target": "mouse.n.01"}, {"source": "animal.n.01", "target": "owl.n.01"}, {"source": "animal.n.01", "target": "giant_panda.n.01"}, {"source": "animal.n.01", "target": "parrot.n.01"}, {"source": "animal.n.01", "target": "penguin.n.01"}, {"source": "animal.n.01", "target": "hog.n.03"}, {"source": "animal.n.01", "target": "gull.n.02"}, {"source": "animal.n.01", "target": "sheep.n.01"}, {"source": "animal.n.01", "target": "snake.n.01"}, {"source": "animal.n.01", "target": "snow_bunting.n.01"}, {"source": "animal.n.01", "target": "starfish.n.01"}, {"source": "animal.n.01", "target": "swan.n.01"}, {"source": "animal.n.01", "target": "zebra.n.01"}, {"source": "animal.n.01", "target": "alligator.n.02"}, {"source": "animal.n.01", "target": "squirrel.n.01"}, {"source": "animal.n.01", "target": "cock.n.04"}, {"source": "animal.n.01", "target": "kitten.n.01"}, {"source": "animal.n.01", "target": "turkey.n.01"}, {"source": "animal.n.01", "target": "hen.n.01"}, {"source": "animal.n.01", "target": "goose.n.01"}, {"source": "animal.n.01", "target": "ant.n.01"}, {"source": "animal.n.01", "target": "lamb.n.01"}, {"source": "tree.n.01", "target": "apple.n.02"}, {"source": "tree.n.01", "target": "avocado.n.02"}, {"source": "tree.n.01", "target": "christmas_bush.n.01"}, {"source": "tree.n.01", "target": "lemon.n.03"}, {"source": "tree.n.01", "target": "orange.n.03"}, {"source": "tree.n.01", "target": "palm.n.03"}, {"source": "tree.n.01", "target": "pear.n.02"}, {"source": "tree.n.01", "target": "coffee.n.02"}, {"source": "girl.n.01", "target": "baby.n.05"}, {"source": "girl.n.01", "target": "dame.n.01"}, {"source": "woman.n.01", "target": "girl.n.01"}, {"source": "woman.n.01", "target": "dame.n.02"}, {"source": "woman.n.01", "target": "mother.n.03"}, {"source": "woman.n.01", "target": "smasher.n.02"}, {"source": "furniture.n.01", "target": "baby_bed.n.01"}, {"source": "furniture.n.01", "target": "table.n.02"}, {"source": "furniture.n.01", "target": "bed.n.01"}, {"source": "furniture.n.01", "target": "seat.n.03"}, {"source": "furniture.n.01", "target": "bookcase.n.01"}, {"source": "furniture.n.01", "target": "cabinet.n.01"}, {"source": "furniture.n.01", "target": "dining_table.n.01"}, {"source": "furniture.n.01", "target": "file.n.03"}, {"source": "furniture.n.01", "target": "floor_lamp.n.01"}, {"source": "furniture.n.01", "target": "table_lamp.n.01"}, {"source": "furniture.n.01", "target": "wardrobe.n.01"}, {"source": "baby_bed.n.01", "target": "crib.n.01"}, {"source": "container.n.01", "target": "baby_buggy.n.01"}, {"source": "container.n.01", "target": "bag.n.01"}, {"source": "container.n.01", "target": "barrel.n.02"}, {"source": "container.n.01", "target": "basket.n.01"}, {"source": "container.n.01", "target": "bathtub.n.01"}, {"source": "container.n.01", "target": "bicycle.n.01"}, {"source": "container.n.01", "target": "motorcycle.n.01"}, {"source": "container.n.01", "target": "bin.n.01"}, {"source": "container.n.01", "target": "gravy_boat.n.01"}, {"source": "container.n.01", "target": "bottle.n.01"}, {"source": "container.n.01", "target": "bowl.n.03"}, {"source": "container.n.01", "target": "box.n.01"}, {"source": "container.n.01", "target": "bucket.n.01"}, {"source": "container.n.01", "target": "canister.n.02"}, {"source": "container.n.01", "target": "car.n.01"}, {"source": "container.n.01", "target": "handcart.n.01"}, {"source": "container.n.01", "target": "case.n.05"}, {"source": "container.n.01", "target": "cup.n.01"}, {"source": "container.n.01", "target": "mug.n.04"}, {"source": "container.n.01", "target": "packet.n.03"}, {"source": "container.n.01", "target": "dustpan.n.02"}, {"source": "container.n.01", "target": "envelope.n.01"}, {"source": "container.n.01", "target": "truck.n.01"}, {"source": "container.n.01", "target": "fishbowl.n.02"}, {"source": "container.n.01", "target": "glass.n.02"}, {"source": "container.n.01", "target": "bag.n.04"}, {"source": "container.n.01", "target": "jar.n.01"}, {"source": "container.n.01", "target": "pepper_shaker.n.01"}, {"source": "container.n.01", "target": "piggy_bank.n.01"}, {"source": "container.n.01", "target": "saltshaker.n.01"}, {"source": "container.n.01", "target": "skateboard.n.01"}, {"source": "container.n.01", "target": "soap_dispenser.n.01"}, {"source": "container.n.01", "target": "tray.n.01"}, {"source": "container.n.01", "target": "tricycle.n.01"}, {"source": "container.n.01", "target": "streetcar.n.01"}, {"source": "container.n.01", "target": "van.n.03"}, {"source": "container.n.01", "target": "cistern.n.02"}, {"source": "container.n.01", "target": "watering_can.n.01"}, {"source": "container.n.01", "target": "sandbox.n.01"}, {"source": "shoe.n.01", "target": "baby_shoe.n.01"}, {"source": "shoe.n.01", "target": "sandal.n.01"}, {"source": "shoe.n.01", "target": "walker.n.04"}, {"source": "shoe.n.01", "target": "gym_shoe.n.01"}, {"source": "footwear.n.02", "target": "shoe.n.01"}, {"source": "footwear.n.02", "target": "slipper.n.01"}, {"source": "bag.n.01", "target": "backpack.n.01"}, {"source": "bag.n.01", "target": "sack.n.01"}, {"source": "bag.n.01", "target": "plastic_bag.n.01"}, {"source": "bread.n.01", "target": "baguet.n.01"}, {"source": "bread.n.01", "target": "cracker.n.01"}, {"source": "bread.n.01", "target": "muffin.n.01"}, {"source": "bread.n.01", "target": "toast.n.01"}, {"source": "food.n.02", "target": "bread.n.01"}, {"source": "food.n.02", "target": "banana.n.02"}, {"source": "food.n.02", "target": "vegetable.n.01"}, {"source": "food.n.02", "target": "cake.n.03"}, {"source": "food.n.02", "target": "meat.n.01"}, {"source": "food.n.02", "target": "raisin.n.01"}, {"source": "ball.n.01", "target": "football.n.02"}, {"source": "ball.n.01", "target": "soccer_ball.n.01"}, {"source": "ball.n.01", "target": "tennis_ball.n.01"}, {"source": "conveyance.n.03", "target": "balloon.n.01"}, {"source": "conveyance.n.03", "target": "bus.n.01"}, {"source": "conveyance.n.03", "target": "airplane.n.01"}, {"source": "conveyance.n.03", "target": "tugboat.n.01"}, {"source": "conveyance.n.03", "target": "train.n.01"}, {"source": "conveyance.n.03", "target": "sled.n.01"}, {"source": "conveyance.n.03", "target": "helicopter.n.01"}, {"source": "flag.n.01", "target": "banner.n.01"}, {"source": "decoration.n.01", "target": "flag.n.01"}, {"source": "decoration.n.01", "target": "bead.n.01"}, {"source": "decoration.n.01", "target": "bracelet.n.02"}, {"source": "decoration.n.01", "target": "necklace.n.01"}, {"source": "decoration.n.01", "target": "spray.n.03"}, {"source": "decoration.n.01", "target": "hanging.n.01"}, {"source": "counter.n.01", "target": "bar.n.02"}, {"source": "table.n.02", "target": "counter.n.01"}, {"source": "table.n.02", "target": "coffee_table.n.01"}, {"source": "table.n.02", "target": "desk.n.01"}, {"source": "table.n.02", "target": "dressing_table.n.01"}, {"source": "table.n.02", "target": "kitchen_table.n.01"}, {"source": "table.n.02", "target": "pool_table.n.01"}, {"source": "rack.n.01", "target": "barbecue.n.03"}, {"source": "rack.n.01", "target": "coatrack.n.01"}, {"source": "rack.n.01", "target": "dish_rack.n.01"}, {"source": "rack.n.01", "target": "towel_rack.n.01"}, {"source": "barrel.n.02", "target": "butt.n.08"}, {"source": "game.n.01", "target": "baseball.n.01"}, {"source": "game.n.01", "target": "board_game.n.01"}, {"source": "game.n.01", "target": "card_game.n.01"}, {"source": "bat.n.05", "target": "baseball_bat.n.01"}, {"source": "stick.n.01", "target": "bat.n.05"}, {"source": "stick.n.01", "target": "drumstick.n.02"}, {"source": "sports_equipment.n.01", "target": "baseball_glove.n.01"}, {"source": "sports_equipment.n.01", "target": "basketball.n.02"}, {"source": "sports_equipment.n.01", "target": "weight.n.02"}, {"source": "sports_equipment.n.01", "target": "hockey_stick.n.01"}, {"source": "sports_equipment.n.01", "target": "iron.n.02"}, {"source": "sports_equipment.n.01", "target": "trampoline.n.01"}, {"source": "basket.n.01", "target": "clothes_hamper.n.01"}, {"source": "basket.n.01", "target": "wicker_basket.n.01"}, {"source": "goal.n.03", "target": "basket.n.03"}, {"source": "goal.n.03", "target": "net.n.04"}, {"source": "room.n.01", "target": "toilet.n.01"}, {"source": "room.n.01", "target": "bedroom.n.01"}, {"source": "room.n.01", "target": "kitchen.n.01"}, {"source": "room.n.01", "target": "boot.n.02"}, {"source": "toilet.n.01", "target": "water_closet.n.01"}, {"source": "plaything.n.01", "target": "beach_ball.n.01"}, {"source": "plaything.n.01", "target": "kite.n.03"}, {"source": "plaything.n.01", "target": "lego.n.01"}, {"source": "plaything.n.01", "target": "slide.n.04"}, {"source": "plaything.n.01", "target": "puppet.n.03"}, {"source": "plaything.n.01", "target": "teddy.n.01"}, {"source": "plaything.n.01", "target": "train_set.n.01"}, {"source": "plaything.n.01", "target": "water_pistol.n.01"}, {"source": "vegetable.n.01", "target": "bean.n.01"}, {"source": "vegetable.n.01", "target": "eggplant.n.01"}, {"source": "vegetable.n.01", "target": "mushroom.n.05"}, {"source": "vegetable.n.01", "target": "pea.n.01"}, {"source": "vegetable.n.01", "target": "tomato.n.01"}, {"source": "bed.n.01", "target": "hammock.n.02"}, {"source": "seat.n.03", "target": "bench.n.01"}, {"source": "seat.n.03", "target": "chair.n.01"}, {"source": "seat.n.03", "target": "sofa.n.01"}, {"source": "seat.n.03", "target": "stool.n.01"}, {"source": "seat.n.03", "target": "toilet_seat.n.01"}, {"source": "bin.n.01", "target": "recycling_bin.n.01"}, {"source": "bin.n.01", "target": "ashcan.n.01"}, {"source": "cage.n.01", "target": "birdcage.n.01"}, {"source": "enclosure.n.01", "target": "cage.n.01"}, {"source": "enclosure.n.01", "target": "fireplace.n.01"}, {"source": "enclosure.n.01", "target": "aquarium.n.01"}, {"source": "enclosure.n.01", "target": "playpen.n.01"}, {"source": "cake.n.03", "target": "cookie.n.01"}, {"source": "cake.n.03", "target": "cupcake.n.01"}, {"source": "cake.n.03", "target": "doughnut.n.02"}, {"source": "cake.n.03", "target": "pancake.n.01"}, {"source": "sheet.n.06", "target": "blackboard.n.01"}, {"source": "sheet.n.06", "target": "board.n.03"}, {"source": "sheet.n.06", "target": "plate.n.02"}, {"source": "sheet.n.06", "target": "slide.n.01"}, {"source": "sheet.n.06", "target": "pane.n.01"}, {"source": "mixer.n.04", "target": "blender.n.01"}, {"source": "mixer.n.04", "target": "electric_mixer.n.01"}, {"source": "mixer.n.04", "target": "whisk.n.01"}, {"source": "kitchen_utensil.n.01", "target": "mixer.n.04"}, {"source": "kitchen_utensil.n.01", "target": "cookie_cutter.n.01"}, {"source": "kitchen_utensil.n.01", "target": "reamer.n.01"}, {"source": "kitchen_utensil.n.01", "target": "pot.n.01"}, {"source": "kitchen_utensil.n.01", "target": "kitchenware.n.01"}, {"source": "kitchen_utensil.n.01", "target": "pan.n.01"}, {"source": "kitchen_utensil.n.01", "target": "spatula.n.01"}, {"source": "utensil.n.01", "target": "kitchen_utensil.n.01"}, {"source": "blind.n.03", "target": "curtain.n.01"}, {"source": "blind.n.03", "target": "window_blind.n.01"}, {"source": "block.n.01", "target": "tablet.n.03"}, {"source": "block.n.01", "target": "tile.n.01"}, {"source": "shrub.n.01", "target": "blueberry.n.01"}, {"source": "shrub.n.01", "target": "tall_mallow.n.01"}, {"source": "shrub.n.01", "target": "cube.n.04"}, {"source": "shrub.n.01", "target": "capsicum.n.01"}, {"source": "board.n.03", "target": "chopping_board.n.01"}, {"source": "board.n.03", "target": "ironing_board.n.01"}, {"source": "book.n.02", "target": "notebook.n.01"}, {"source": "shelf.n.01", "target": "bookshelf.n.01"}, {"source": "bottle.n.01", "target": "water_bottle.n.01"}, {"source": "bottle.n.01", "target": "water_jug.n.01"}, {"source": "bottle.n.01", "target": "wine_bottle.n.01"}, {"source": "weapon.n.01", "target": "bow.n.04"}, {"source": "weapon.n.01", "target": "grapeshot.n.01"}, {"source": "weapon.n.01", "target": "knife.n.02"}, {"source": "bowl.n.03", "target": "soup_bowl.n.01"}, {"source": "box.n.01", "target": "cereal_box.n.01"}, {"source": "box.n.01", "target": "mailbox.n.01"}, {"source": "box.n.01", "target": "pencil_box.n.01"}, {"source": "box.n.01", "target": "toolbox.n.01"}, {"source": "box.n.01", "target": "toy_box.n.01"}, {"source": "man.n.01", "target": "boy.n.02"}, {"source": "man.n.01", "target": "guy.n.01"}, {"source": "man.n.01", "target": "wolf.n.04"}, {"source": "surface.n.01", "target": "bridge.n.09"}, {"source": "surface.n.01", "target": "ceiling.n.01"}, {"source": "surface.n.01", "target": "chessboard.n.01"}, {"source": "surface.n.01", "target": "countertop.n.01"}, {"source": "surface.n.01", "target": "face.n.04"}, {"source": "surface.n.01", "target": "brim.n.01"}, {"source": "surface.n.01", "target": "nose.n.02"}, {"source": "brush.n.02", "target": "hairbrush.n.01"}, {"source": "brush.n.02", "target": "paintbrush.n.01"}, {"source": "brush.n.02", "target": "toothbrush.n.01"}, {"source": "ball.n.03", "target": "bubble.n.01"}, {"source": "building.n.01", "target": "house.n.01"}, {"source": "building.n.01", "target": "grillroom.n.01"}, {"source": "building.n.01", "target": "shed.n.01"}, {"source": "building.n.01", "target": "garage.n.01"}, {"source": "rabbit.n.01", "target": "bunny.n.02"}, {"source": "cable.n.02", "target": "power_line.n.01"}, {"source": "cactus.n.01", "target": "tuna.n.01"}, {"source": "machine.n.01", "target": "calculator.n.02"}, {"source": "machine.n.01", "target": "computer.n.01"}, {"source": "machine.n.01", "target": "pepper_mill.n.01"}, {"source": "machine.n.01", "target": "printer.n.02"}, {"source": "machine.n.01", "target": "record_player.n.01"}, {"source": "machine.n.01", "target": "power_shovel.n.01"}, {"source": "machine.n.01", "target": "treadmill.n.02"}, {"source": "tool.n.01", "target": "can_opener.n.01"}, {"source": "tool.n.01", "target": "lawn_mower.n.01"}, {"source": "tool.n.01", "target": "paper_cutter.n.01"}, {"source": "tool.n.01", "target": "scissors.n.01"}, {"source": "tool.n.01", "target": "screwdriver.n.01"}, {"source": "lamp.n.01", "target": "candle.n.01"}, {"source": "lamp.n.01", "target": "flashlight.n.01"}, {"source": "lamp.n.01", "target": "lantern.n.01"}, {"source": "lamp.n.01", "target": "light_bulb.n.01"}, {"source": "candy.n.01", "target": "candy_cane.n.01"}, {"source": "candy.n.01", "target": "lollipop.n.02"}, {"source": "clothing.n.01", "target": "cap.n.01"}, {"source": "clothing.n.01", "target": "hosiery.n.01"}, {"source": "clothing.n.01", "target": "coat.n.01"}, {"source": "clothing.n.01", "target": "diaper.n.01"}, {"source": "clothing.n.01", "target": "dress.n.01"}, {"source": "clothing.n.01", "target": "hat.n.01"}, {"source": "clothing.n.01", "target": "trouser.n.01"}, {"source": "clothing.n.01", "target": "mask.n.01"}, {"source": "clothing.n.01", "target": "shirt.n.01"}, {"source": "clothing.n.01", "target": "sweater.n.01"}, {"source": "clothing.n.01", "target": "ballet_skirt.n.01"}, {"source": "clothing.n.01", "target": "mitten.n.01"}, {"source": "clothing.n.01", "target": "scarf.n.01"}, {"source": "clothing.n.01", "target": "snowsuit.n.01"}, {"source": "door.n.01", "target": "car_door.n.01"}, {"source": "wheel.n.01", "target": "car_wheel.n.01"}, {"source": "wheel.n.01", "target": "roller.n.03"}, {"source": "cardboard.n.01", "target": "card.n.04"}, {"source": "paper.n.01", "target": "cardboard.n.01"}, {"source": "paper.n.01", "target": "tissue.n.02"}, {"source": "handcart.n.01", "target": "shopping_cart.n.01"}, {"source": "handcart.n.01", "target": "barrow.n.03"}, {"source": "case.n.05", "target": "bag.n.06"}, {"source": "case.n.05", "target": "wallet.n.01"}, {"source": "grass.n.01", "target": "cereal.n.01"}, {"source": "cereal.n.01", "target": "corn.n.01"}, {"source": "necklace.n.01", "target": "chain.n.09"}, {"source": "chair.n.01", "target": "wheelchair.n.01"}, {"source": "writing_implement.n.01", "target": "chalk.n.04"}, {"source": "writing_implement.n.01", "target": "crayon.n.01"}, {"source": "writing_implement.n.01", "target": "marker.n.03"}, {"source": "writing_implement.n.01", "target": "pencil.n.01"}, {"source": "fixture.n.01", "target": "chandelier.n.01"}, {"source": "fixture.n.01", "target": "sink.n.01"}, {"source": "fixture.n.01", "target": "toilet.n.02"}, {"source": "fixture.n.01", "target": "shower.n.01"}, {"source": "fixture.n.01", "target": "soap_dish.n.01"}, {"source": "fixture.n.01", "target": "water_faucet.n.01"}, {"source": "horse.n.01", "target": "charger.n.01"}, {"source": "horse.n.01", "target": "post_horse.n.01"}, {"source": "horse.n.01", "target": "pony.n.01"}, {"source": "meat.n.01", "target": "chicken.n.01"}, {"source": "meat.n.01", "target": "pepperoni.n.01"}, {"source": "meat.n.01", "target": "shoulder.n.02"}, {"source": "child.n.01", "target": "toddler.n.01"}, {"source": "tableware.n.01", "target": "chopstick.n.01"}, {"source": "tableware.n.01", "target": "crockery.n.01"}, {"source": "tableware.n.01", "target": "fork.n.01"}, {"source": "tableware.n.01", "target": "glass.n.07"}, {"source": "tableware.n.01", "target": "paper_plate.n.01"}, {"source": "tableware.n.01", "target": "silverware.n.01"}, {"source": "tableware.n.01", "target": "spoon.n.01"}, {"source": "present.n.02", "target": "christmas_present.n.01"}, {"source": "gift.n.01", "target": "present.n.02"}, {"source": "stocking.n.01", "target": "christmas_stocking.n.01"}, {"source": "hosiery.n.01", "target": "stocking.n.01"}, {"source": "hosiery.n.01", "target": "sock.n.01"}, {"source": "fabric.n.01", "target": "towel.n.01"}, {"source": "fabric.n.01", "target": "bib.n.01"}, {"source": "cord.n.01", "target": "clothesline.n.01"}, {"source": "cord.n.01", "target": "thread.n.01"}, {"source": "coat.n.01", "target": "jacket.n.01"}, {"source": "beverage.n.01", "target": "coca_cola.n.01"}, {"source": "beverage.n.01", "target": "milk.n.01"}, {"source": "beverage.n.01", "target": "pop.n.02"}, {"source": "beverage.n.01", "target": "cocoa.n.01"}, {"source": "cup.n.01", "target": "coffee_cup.n.01"}, {"source": "cup.n.01", "target": "dixie_cup.n.01"}, {"source": "home_appliance.n.01", "target": "coffee_maker.n.01"}, {"source": "home_appliance.n.01", "target": "dishwasher.n.01"}, {"source": "home_appliance.n.01", "target": "refrigerator.n.01"}, {"source": "home_appliance.n.01", "target": "microwave.n.02"}, {"source": "home_appliance.n.01", "target": "oven.n.01"}, {"source": "home_appliance.n.01", "target": "toaster_oven.n.01"}, {"source": "home_appliance.n.01", "target": "vacuum.n.04"}, {"source": "home_appliance.n.01", "target": "washer.n.03"}, {"source": "mug.n.04", "target": "coffee_mug.n.01"}, {"source": "coin.n.01", "target": "penny.n.02"}, {"source": "body_part.n.01", "target": "comb.n.04"}, {"source": "body_part.n.01", "target": "finger.n.01"}, {"source": "body_part.n.01", "target": "tissue.n.01"}, {"source": "body_part.n.01", "target": "toe.n.01"}, {"source": "body_part.n.01", "target": "nail.n.01"}, {"source": "body_part.n.01", "target": "head.n.01"}, {"source": "body_part.n.01", "target": "penis.n.01"}, {"source": "body_part.n.01", "target": "ankle.n.01"}, {"source": "body_part.n.01", "target": "stomach.n.01"}, {"source": "body_part.n.01", "target": "auricle.n.02"}, {"source": "body_part.n.01", "target": "mouth.n.01"}, {"source": "body_part.n.01", "target": "cheek.n.01"}, {"source": "body_part.n.01", "target": "eye.n.01"}, {"source": "body_part.n.01", "target": "vagina.n.01"}, {"source": "body_part.n.01", "target": "knee.n.01"}, {"source": "computer.n.01", "target": "laptop.n.01"}, {"source": "monitor.n.04", "target": "computer_monitor.n.01"}, {"source": "control.n.09", "target": "switch.n.01"}, {"source": "control.n.09", "target": "faucet.n.01"}, {"source": "control.n.09", "target": "steering_wheel.n.01"}, {"source": "corn.n.01", "target": "popcorn.n.01"}, {"source": "sofa.n.01", "target": "convertible.n.03"}, {"source": "melon.n.02", "target": "cucumber.n.01"}, {"source": "melon.n.02", "target": "watermelon.n.01"}, {"source": "curtain.n.01", "target": "shower_curtain.n.01"}, {"source": "packet.n.03", "target": "deck.n.02"}, {"source": "deer.n.01", "target": "caribou.n.01"}, {"source": "deer.n.01", "target": "elk.n.01"}, {"source": "disk.n.02", "target": "frisbee.n.01"}, {"source": "dish.n.02", "target": "pizza.n.01"}, {"source": "dish.n.02", "target": "chip.n.04"}, {"source": "dish.n.02", "target": "sandwich.n.01"}, {"source": "dish.n.02", "target": "soup.n.01"}, {"source": "dish.n.02", "target": "sushi.n.01"}, {"source": "dish.n.02", "target": "pudding.n.01"}, {"source": "dish.n.02", "target": "applesauce.n.01"}, {"source": "dish.n.02", "target": "pasta.n.01"}, {"source": "dog.n.01", "target": "pug.n.01"}, {"source": "dog.n.01", "target": "toy_dog.n.01"}, {"source": "dog.n.01", "target": "puppy.n.01"}, {"source": "house.n.01", "target": "dollhouse.n.01"}, {"source": "fish.n.01", "target": "dolphinfish.n.02"}, {"source": "fish.n.01", "target": "shark.n.01"}, {"source": "switch.n.01", "target": "doorbell.n.01"}, {"source": "dough.n.01", "target": "pastry.n.01"}, {"source": "monkey.n.01", "target": "drill.n.02"}, {"source": "musical_instrument.n.01", "target": "drum.n.01"}, {"source": "musical_instrument.n.01", "target": "guitar.n.01"}, {"source": "musical_instrument.n.01", "target": "harp.n.01"}, {"source": "musical_instrument.n.01", "target": "music_box.n.01"}, {"source": "musical_instrument.n.01", "target": "piano.n.01"}, {"source": "musical_instrument.n.01", "target": "wind_instrument.n.01"}, {"source": "musical_instrument.n.01", "target": "bowed_stringed_instrument.n.01"}, {"source": "drum.n.01", "target": "tambourine.n.01"}, {"source": "drumstick.n.02", "target": "mallet.n.02"}, {"source": "duck.n.01", "target": "scoter.n.01"}, {"source": "weight.n.02", "target": "dumbbell.n.01"}, {"source": "earphone.n.01", "target": "telephone_receiver.n.01"}, {"source": "tripod.n.01", "target": "easel.n.01"}, {"source": "fence.n.01", "target": "stone_wall.n.01"}, {"source": "fence.n.01", "target": "wall.n.07"}, {"source": "fireplace.n.01", "target": "fire.n.04"}, {"source": "tube.n.01", "target": "fireplug.n.01"}, {"source": "tube.n.01", "target": "garden_hose.n.01"}, {"source": "tube.n.01", "target": "straw.n.04"}, {"source": "tube.n.01", "target": "hookah.n.01"}, {"source": "truck.n.01", "target": "fire_engine.n.01"}, {"source": "truck.n.01", "target": "tractor.n.02"}, {"source": "floor.n.02", "target": "basement.n.01"}, {"source": "flower.n.01", "target": "vanilla.n.01"}, {"source": "photograph.n.01", "target": "frame.n.02"}, {"source": "refrigerator.n.01", "target": "electric_refrigerator.n.01"}, {"source": "fruit.n.01", "target": "nut.n.01"}, {"source": "yard.n.02", "target": "garden.n.03"}, {"source": "yard.n.02", "target": "playground.n.02"}, {"source": "land.n.04", "target": "spit.n.01"}, {"source": "guitar.n.01", "target": "uke.n.01"}, {"source": "heater.n.01", "target": "radiator.n.02"}, {"source": "heater.n.01", "target": "stove.n.02"}, {"source": "jar.n.01", "target": "vase.n.01"}, {"source": "trouser.n.01", "target": "jean.n.01"}, {"source": "trouser.n.01", "target": "pajama.n.01"}, {"source": "puzzle.n.02", "target": "jigsaw_puzzle.n.01"}, {"source": "pot.n.01", "target": "kettle.n.01"}, {"source": "pot.n.01", "target": "teapot.n.01"}, {"source": "sink.n.01", "target": "kitchen_sink.n.01"}, {"source": "knife.n.02", "target": "dagger.n.01"}, {"source": "stairway.n.01", "target": "ladder.n.01"}, {"source": "pad.n.04", "target": "mattress.n.01"}, {"source": "pad.n.04", "target": "table_mat.n.01"}, {"source": "microphone.n.01", "target": "bug.n.03"}, {"source": "stool.n.01", "target": "footstool.n.01"}, {"source": "pan.n.01", "target": "saucepan.n.01"}, {"source": "pan.n.01", "target": "spider.n.03"}, {"source": "towel.n.01", "target": "paper_towel.n.01"}, {"source": "wind_instrument.n.01", "target": "pipe.n.04"}, {"source": "plate.n.02", "target": "tap.n.04"}, {"source": "racket.n.04", "target": "tennis_racket.n.01"}, {"source": "hoop.n.02", "target": "tire.n.01"}, {"source": "road.n.01", "target": "street.n.01"}, {"source": "sandwich.n.01", "target": "hamburger.n.01"}, {"source": "sauce.n.01", "target": "tomato_sauce.n.01"}, {"source": "spoon.n.01", "target": "soupspoon.n.01"}, {"source": "bowed_stringed_instrument.n.01", "target": "violin.n.01"}, {"source": "sweater.n.01", "target": "turtleneck.n.01"}, {"source": "electronic_equipment.n.01", "target": "telephone.n.01"}, {"source": "electronic_equipment.n.01", "target": "radio_receiver.n.01"}, {"source": "telephone_wire.n.01", "target": "telephone_cord.n.01"}, {"source": "wire.n.02", "target": "telephone_wire.n.01"}, {"source": "tissue.n.01", "target": "tooth.n.01"}, {"source": "tissue.n.02", "target": "toilet_tissue.n.01"}, {"source": "window_blind.n.01", "target": "window_shade.n.01"}, {"source": "cracker.n.01", "target": "pretzel.n.01"}]}